bluearchive/__init__.py
bluearchive/api.py
bluearchive/log.py
bluearchive/query.py
bluearchive/types.py
bluearchive/models/__init__.py
bluearchive/models/abc.py
bluearchive/models/base.py
bluearchive/models/enums.py
bluearchive/models/student.py
bluearchive-1.1.2.dist-info/METADATA
bluearchive-1.1.2.dist-info/WHEEL
bluearchive-1.1.2.dist-info/top_level.txt
bluearchive-1.1.2.dist-info/RECORD
